patreon_archiver/__init__.py
patreon_archiver/__main__.py
patreon_archiver/constants.py
patreon_archiver/main.py
patreon_archiver/py.typed
patreon_archiver/typing.py
patreon_archiver/typing.ts
patreon_archiver/utils.py
patreon_archiver-0.1.5.dist-info/METADATA
patreon_archiver-0.1.5.dist-info/WHEEL
patreon_archiver-0.1.5.dist-info/entry_points.txt
patreon_archiver-0.1.5.dist-info/licenses/LICENSE.txt
patreon_archiver-0.1.5.dist-info/RECORD
