Metadata-Version: 2.4
Name: patreon-archiver
Version: 0.1.5
Summary: Save Patreon content you have access to.
License-Expression: MIT
License-File: LICENSE.txt
Keywords: command line,patreon
Author: Andrew Udvare
Author-email: audvare@gmail.com
Requires-Python: >=3.12,<4.0
Classifier: Development Status :: 4 - Beta
Classifier: Intended Audience :: Developers
Classifier: Programming Language :: Python
Classifier: Programming Language :: Python :: 3.12
Classifier: Programming Language :: Python :: 3.13
Classifier: Typing :: Typed
Requires-Dist: bascom (>=0.1.0,<0.2.0)
Requires-Dist: click (>=8.3.1,<9.0.0)
Requires-Dist: requests (>=2.32.5,<3.0.0)
Requires-Dist: typing-extensions (>=4.15.0,<5.0.0)
Requires-Dist: yt-dlp-utils (>=0.0.6,<0.0.7)
Project-URL: Documentation, https://patreon-archiver.readthedocs.org
Project-URL: Homepage, https://tatsh.github.io/patreon-archiver/
Project-URL: Issues, https://github.com/Tatsh/patreon-archiver/issues
Project-URL: Repository, https://github.com/Tatsh/patreon-archiver
